pylomena/__init__.py
pylomena/api.py
pylomena/matcher.py
pylomena/py.typed
pylomena/sites.py
pylomena/types.py
pylomena/utils.py
pylomena-0.0.3.dist-info/LICENSE
pylomena-0.0.3.dist-info/METADATA
pylomena-0.0.3.dist-info/WHEEL
pylomena-0.0.3.dist-info/top_level.txt
pylomena-0.0.3.dist-info/RECORD
