Metadata-Version: 2.1
Name: pylomena
Version: 0.0.3
Summary: Python client for accessing Philomena based imageboards
Author-email: Flynn <flynnmlp@gmail.com>
Project-URL: Homepage, https://github.com/flynnmlp/pylomena
Project-URL: Bug Tracker, https://github.com/flynnmlp/pylomena/issues
Classifier: Programming Language :: Python :: 3
Classifier: License :: OSI Approved :: GNU General Public License v3 (GPLv3)
Classifier: Operating System :: OS Independent
Requires-Python: >=3.7
License-File: LICENSE
Requires-Dist: python-dateutil (~=2.8.2)
Requires-Dist: requests (~=2.28.2)
Requires-Dist: levenshtein (~=0.20.9)
Provides-Extra: all
Requires-Dist: pylomena[testing] ; extra == 'all'
Provides-Extra: testing
Requires-Dist: flake8 (>=5.0.4) ; extra == 'testing'
Requires-Dist: Flake8-pyproject (~=1.2.2) ; extra == 'testing'
Requires-Dist: mypy (~=1.0.1) ; extra == 'testing'
Requires-Dist: types-python-dateutil (~=2.8.19.6) ; extra == 'testing'
Requires-Dist: types-requests (~=2.28.11.12) ; extra == 'testing'
Requires-Dist: tox ; extra == 'testing'
